{
  "page_content": "National Seminar on Recent Advances in Life Sciences and Biotechnology \n\n\n\n27th February 2023\t\t\t\t\t\t\n\n\n\n\n\n\n\n\n\n\n\n\n\n\n\n\n\n \n\n\n\n\n\n\n\n72nd International Workshop on Great Lessons from Paulo Freire \n\n\n\n11th February 2023\t\t\t\t\t\t\n\n\n\n\n\n\n\n\n\n\n\n\n\n\n\n\n\n \n\n\n\n\n\n\n\n66th International Workshop on Research and Development \n\n\n\n10th February 2023\t\t\t\t\t\t\n\n\n\n\n\n\n\n\n\n\n\n\n\n\n\n\n\n \n\n\n\n\n\n\n\n71st International Workshop on Life Lessons from Thomas Hobbes \n\n\n\n4th February 2023\t\t\t\t\t\t\n\n\n\n\n\n\n\n\n\n\n\n\n\n\n\n\n\n \n\n\n\n\n\n\n\n65th International Workshop on Qualitative and Quantitative Mixed Methods \n\n\n\n3rd February 2023\t\t\t\t\t\t\n\n\n\n\n\n\n\n\n\n\n\n\n\n\n\n\n\n\n\n\n\n\n\n\n\n\n\n\n\n\n\n\nKnow your people\n \n\n\n\n\n\n\n\n\n\n\n\n\n\n\n\nVice-Chancellor's MessageProf. V. Srikanth Reddy Sri Venkateswara University, \n\n\n\n\n\n\n\n\n\n\n\nRegistrar's Message \n\n\n\nRector's Message \n\n\n\n\n\n\n\nRegistrar's Message \n\n\n\n\n\n\n\n\n\n\n\nVice-Chancellor's MessageProf. V. Srikanth Reddy Sri Venkateswara University, \n\n\n\n\n\n\n\n\n\n\n\n\n\n\n\n\n\n\n\nRegistrar's Message \n\n\n\n\n\n\n\n\n\n\n\nFaculty Search",
  "metadata": {
    "source": "https://svuniversity.edu.in/",
    "title": "Sri Venkateswara University, Tirupati  – NAAC A+ Accredited",
    "language": "en-US"
  }
}