{
  "page_content": "INTERNATIONAL CONFERENCE ON INDIA AS AN EMERGING GLOBAL POWER: THE JOURNEY TOWARDS VIKASIT BHARAT @ 2047 Organized by DEPARTMENT OF POLITICAL SCIENCE AND PUBLIC ADMINISTRATION\t\t\t\n\n\nINTERNATIONAL CONFERENCE ON INDIA AS AN EMERGING GLOBAL POWER: THE JOURNEY TOWARDS VIKASIT BHARAT @ 2047 Organized by DEPARTMENT OF POLITICAL SCIENCE AND PUBLIC ADMINISTRATION\n\n\n\n\n\n\n\n\n\n\t\t\t\tANUSANDHAN NATIONAL RESEARCH FOUNDATION (ANRF) PARTNER FOR ACCELERATED INNOVATION AND RESEARCH (PAIR) PROGRAM APPOINMENT OF PRINCIPAL INVESTIGATOR AND CO-PRINCIPAL INVESTIGATOR FOR THE POINT OF CONTACT\t\t\t\n\n\nANUSANDHAN NATIONAL RESEARCH FOUNDATION (ANRF) PARTNER FOR ACCELERATED INNOVATION AND RESEARCH (PAIR) PROGRAM APPOINMENT OF PRINCIPAL INVESTIGATOR AND CO-PRINCIPAL INVESTIGATOR FOR THE POINT OF CONTACT\n\n\n\n\n\n\n\n\n\n\t\t\t\tIncome Tax Form for FY 2024-25\t\t\t\n\n\nIT Form-2024\n\n\n\n\n\n\n\n\n\n\t\t\t\tInviting quotations from reputed Printers\t\t\t\n\n\nNotification Detail for Notification Annexure",
  "metadata": {
    "source": "https://svuniversity.edu.in/",
    "title": "Sri Venkateswara University, Tirupati  – NAAC A+ Accredited",
    "language": "en-US"
  }
}